[
  {
    "id": 1,
    "status": "x",
    "taskName": "nunggu gofood",
    "date": "2018-05-09T13:08:40.495Z"
  },
  {
    "id": 2,
    "status": "",
    "taskName": "akirnya gofood dateng",
    "date": "2018-05-09T13:14:29.091Z"
  },
  {
    "id": 3,
    "status": "x",
    "taskName": "tidur sambil makan",
    "date": "2018-05-09T13:46:49.921Z"
  },
  {
    "id": 4,
    "status": "",
    "taskName": "lompat",
    "date": "2018-05-09T13:47:11.498Z"
  },
  {
    "id": 5,
    "status": "x",
    "taskName": "berlari",
    "date": "2018-05-09T13:47:27.778Z"
  },
  {
    "id": 7,
    "status": "",
    "taskName": "minum",
    "date": "2018-05-09T15:33:43.983Z"
  },
  {
    "id": 8,
    "status": "",
    "taskName": "minum",
    "date": "2018-05-09T15:34:13.271Z"
  }
]